nanga_ad_library/__init__.py
nanga_ad_library/exceptions.py
nanga_ad_library/sdk.py
nanga_ad_library/sessions.py
nanga_ad_library/ad_downloaders/__init__.py
nanga_ad_library/ad_downloaders/meta_ad_downloader.py
nanga_ad_library/ad_libraries/__init__.py
nanga_ad_library/ad_libraries/meta_ad_library.py
nanga_ad_library/utils/__init__.py
nanga_ad_library/utils/ad_libraries_config.py
nanga_ad_library/utils/object_parser.py
nanga_ad_library/utils/param_checker.py
nanga_ad_library/utils/request_handler.py
nanga_ad_library/utils/user_agents.txt
nanga_ad_library/utils/version.py
nanga_ad_library-1.2.0.dist-info/licenses/LICENSE
nanga_ad_library-1.2.0.dist-info/METADATA
nanga_ad_library-1.2.0.dist-info/WHEEL
nanga_ad_library-1.2.0.dist-info/top_level.txt
nanga_ad_library-1.2.0.dist-info/RECORD
