Metadata-Version: 2.4
Name: nanga-ad-library
Version: 1.2.0
Summary: The Nanga Ad Library developed by the ⭐️ Spark Tech team
Home-page: https://github.com/Spark-Data-Team/nanga-ad-library
Download-URL: https://github.com/Spark-Data-Team/nanga-ad-library/tarball/1.2.0
Author: Nanga
Author-email: hello@spark.do
License: GNU General Public License v3 (GPLv3) (gpl-3.0)
License-File: LICENSE
Requires-Dist: requests>=2.3.0
Requires-Dist: curlify>=2.1.0
Requires-Dist: playwright>=1.49.0
Requires-Dist: python-dateutil>=2.9.0.post0
Dynamic: author
Dynamic: author-email
Dynamic: description
Dynamic: description-content-type
Dynamic: download-url
Dynamic: home-page
Dynamic: license
Dynamic: license-file
Dynamic: requires-dist
Dynamic: summary
